[
    {

        "type": "رجل",
        "answers": ["ارجل"]
    },
    {
	        "type": "حبيب",
        "answers": ["احبه"]
    },
    {
	        "type": "قناه",
        "answers": ["قنوات"]
    },
    {
	        "type": "فتاه",
        "answers": ["فتايات"]
    },
    {
	        "type": "سياره",
        "answers": ["سيارات"]
    },
    {
	        "type": "واحد",
        "answers": ["", "", "واحدان", ",واحدون"]
    },
    {
	        "type": "بطاريه",
        "answers": ["بطاريات"]
    },
    {

	        "type": "اخطبوط",
        "answers": ["اخاطيب"]
    },
    {
	        "type": "ملعب",
        "answers": ["ملاعب"]
    },
    {
	        "type": "كم كلمه في كم",
        "answers": ["ك م ك ل م ه ف ي ك م"]
    },
    {
	        "type": "قعقاع فوق قعقاع",
        "answers": ["ق ع ق ا ع ف و ق ق ع ق ا ع"]
    },
    {
	        "type": "جو جدة زي جو جيزان",
        "answers": ["ج و ج د ة ز ي ج و ج ي ز ا ن"]
    },
    {
	        "type": "فراش فراس مفروش",
        "answers": ["ف ر ا ش ف ر ا س م ف ر و ش"]
    },
    {
	        "type": "لقمه و جغمه",
        "answers": ["ل ق م ه و ج غ م ه"]
    },
    {
	        "type": "صفحة سبعة صعبة",
        "answers": ["ص ف ح ة س ب ع ة ص ع ب ة"]
    },
    {
	        "type": "لوري بلا بوري",
        "answers": ["ل و ر ي ب ل ا ب و ر ي"]
    },
    {
	        "type": "شعبان شبعان",
        "answers": ["ش ع ب ا ن ش ب ع ا ن"]
    },
    {
	        "type": "شرطي أكل طرشي",
        "answers": ["ش ر ط ي أ ك ل ط ر ش ي"]
    },
    {
	        "type": "الشاعر في الشارع",
        "answers": ["ا ل ش ا ع ر ف ي ا ل ش ا ر ع"]
    },
    {
	        "type": "خيط حرير على حيط خليل",
        "answers": ["خ ي ط ح ر ي ر ع ل ى ح ي ط خ ل ي ل"]
    },
    {
		        "type": "يالله ياقلبي تعبنى",
        "answers": ["ي ا ل ل ه ي ا ق ل ب ي ت ع ب ن ي"]
    },
    {
    
        "type": "عبدوو",
        "answers": ["ع ب د و و"]
    }
]
